data_uri_parser/__init__.py
data_uri_parser-0.1.11.dist-info/LICENSE
data_uri_parser-0.1.11.dist-info/WHEEL
data_uri_parser-0.1.11.dist-info/METADATA
data_uri_parser-0.1.11.dist-info/RECORD
