Metadata-Version: 2.1
Name: data-uri-parser
Version: 0.1.11
Summary: A Pythonic data uri parser
Home-page: https://github.com/unmadeworks/data_uri_parser/
License: MIT
Author: Unmade
Author-email: backend@unmade.com
Requires-Python: >=3.6,<4.0
Classifier: License :: OSI Approved :: MIT License
Classifier: Programming Language :: Python :: 3
Classifier: Programming Language :: Python :: 3.10
Classifier: Programming Language :: Python :: 3.6
Classifier: Programming Language :: Python :: 3.7
Classifier: Programming Language :: Python :: 3.8
Classifier: Programming Language :: Python :: 3.9
